cannuckfind/C3.py
cannuckfind/__init__.py
cannuckfind/geocasual.py
cannuckfind/geolocation.py
cannuckfind/inDat.py
cannuckfind-0.0.10.dist-info/LICENSE
cannuckfind-0.0.10.dist-info/METADATA
cannuckfind-0.0.10.dist-info/WHEEL
cannuckfind-0.0.10.dist-info/top_level.txt
cannuckfind-0.0.10.dist-info/RECORD
