Metadata-Version: 2.1
Name: cannuckfind
Version: 0.0.10
Summary: Provide an easy interface to geolocation libraries
Maintainer-email: Harold Henson <economisthenson@gmail.com>
Project-URL: documentation, https://hehenson.github.io/cannuckfind/
License-File: LICENSE
